{
  "fields": [
        {
          "key": "bescheidtexte",
          "label": "Bescheidtexte in KM-V",
          "text": "Wurden die Textbausteine und deren Inhalt (Bescheidtexte) vollst채ndig bearbeitet und gepr체ft?",
          "size": 6,
          "inputType": "checkbox"
        },
        {
          "key": "sachbearbeiterangaben",
          "label": "Sachbearbeiterangaben im KM-V",
          "text": "Wurden die Sachbearbeiterangaben und deren Zuordnung vollst채ndig bearbeitet und gepr체ft?",
          "size": 6,
          "inputType": "checkbox"
        }
      ]
}